wust/__init__.py
wust/wekeo_user_support_tools.py
wust-0.1.10.dist-info/WHEEL
wust-0.1.10.dist-info/METADATA
wust-0.1.10.dist-info/RECORD
